pybbxgo/__init__.py
pybbxgo/constants.py
pybbxgo/maqueen.py
pybbxgo/utils.py
pybbxgo/xgo.py
pybbxgo-0.6.dist-info/METADATA
pybbxgo-0.6.dist-info/WHEEL
pybbxgo-0.6.dist-info/top_level.txt
pybbxgo-0.6.dist-info/RECORD
